{"cameraMode":{"drawMode":0,"name":"Shaded","section":"Shading Mode"},"sceneLighting":true,"audioPlay":false,"sceneViewState":{"m_AlwaysRefresh":false,"showFog":true,"showSkybox":true,"showFlares":true,"showImageEffects":true,"showParticleSystems":true,"showVisualEffectGraphs":true,"m_FxEnabled":true},"in2DMode":false,"pivot":{"x":-15.491411209106446,"y":-9.62099552154541,"z":4.814449787139893},"rotation":{"x":-0.20229443907737733,"y":0.3264620304107666,"z":-0.07172523438930512,"w":-0.9205516576766968},"size":14.934704780578614,"orthographic":false}